jcal/__init__.py
jcal/__main__.py
jcal/py.typed
jcal-1.2.2.dist-info/METADATA
jcal-1.2.2.dist-info/WHEEL
jcal-1.2.2.dist-info/entry_points.txt
jcal-1.2.2.dist-info/licenses/LICENSE
jcal-1.2.2.dist-info/RECORD
