Metadata-Version: 2.4
Name: jcal
Version: 1.2.2
Summary: `jcal` is a package for Japanese holiday.
Project-URL: homepage, https://github.com/SaitoTsutomu/jcal
Author-email: Saito Tsutomu <tsutomu7@hotmail.co.jp>
License: Apache-2.0
License-File: LICENSE
Classifier: Development Status :: 1 - Planning
Classifier: License :: OSI Approved :: Apache Software License
Classifier: Programming Language :: Python
Classifier: Topic :: Scientific/Engineering
Classifier: Topic :: Software Development
Requires-Python: >=3.11
